ka_app_mail/__init__.py
ka_app_mail/__version__.py
ka_app_mail/do.py
ka_app_mail/mail.py
ka_app_mail/mailrcv.py
ka_app_mail/mailsnd.py
ka_app_mail/parms.py
ka_app_mail/py.typed
ka_app_mail/task.py
ka_app_mail/ioc/jinja2_.py
ka_app_mail/ioc/yaml_.py
ka_app_mail-4.1.0.250601.dist-info/licenses/LICENSE.txt
ka_app_mail-4.1.0.250601.dist-info/METADATA
ka_app_mail-4.1.0.250601.dist-info/WHEEL
ka_app_mail-4.1.0.250601.dist-info/entry_points.txt
ka_app_mail-4.1.0.250601.dist-info/top_level.txt
ka_app_mail-4.1.0.250601.dist-info/RECORD
